mlflow/__init__.py
mlflow/interpretability/__init__.py
mlflow/interpretability/explainer.py
mlflow/models/__init__.py
mlflow/models/ensemble.py
mlflow/models/gradient_boosting.py
mlflow/models/neural_network.py
mlflow/optimization/__init__.py
mlflow/optimization/bayesian.py
mlflow/optimization/genetic.py
mlflow/utils/__init__.py
mlflow/utils/metrics.py
mlflow/utils/preprocessing.py
mlflow/utils/profiler.py
mlflow/utils/validation.py
mlflow_advanced-1.0.0.dist-info/METADATA
mlflow_advanced-1.0.0.dist-info/WHEEL
mlflow_advanced-1.0.0.dist-info/top_level.txt
mlflow_advanced-1.0.0.dist-info/RECORD
